TOPSIS/__init__.py
TOPSIS/topsis.py
Tahil-1.0.0.dist-info/License.txt
Tahil-1.0.0.dist-info/METADATA
Tahil-1.0.0.dist-info/WHEEL
Tahil-1.0.0.dist-info/entry_points.txt
Tahil-1.0.0.dist-info/top_level.txt
Tahil-1.0.0.dist-info/RECORD
