Metadata-Version: 2.1
Name: Tahil
Version: 1.0.0
Summary: TOPSIS
Home-page: UNKNOWN
Author: Tahil
License: MIT
Platform: UNKNOWN
Classifier: License :: OSI Approved :: MIT License
Classifier: Programming Language :: Python :: 3.6
Classifier: Programming Language :: Python :: 3.7
Classifier: Programming Language :: Python :: 3.8
